akoya_sdk_sdk-1.1.2.dist-info/licenses/LICENSE
akoyaapisv240/__init__.py
akoyaapisv240/akoyaapisv_240_client.py
akoyaapisv240/api_helper.py
akoyaapisv240/configuration.py
akoyaapisv240/controllers/__init__.py
akoyaapisv240/controllers/account_information_controller.py
akoyaapisv240/controllers/balances_controller.py
akoyaapisv240/controllers/base_controller.py
akoyaapisv240/controllers/customers_controller.py
akoyaapisv240/controllers/investments_controller.py
akoyaapisv240/controllers/o_auth_authorization_controller.py
akoyaapisv240/controllers/payments_controller.py
akoyaapisv240/controllers/statements_controller.py
akoyaapisv240/controllers/tax_controller.py
akoyaapisv240/controllers/transactions_controller.py
akoyaapisv240/exceptions/__init__.py
akoyaapisv240/exceptions/api_exception.py
akoyaapisv240/exceptions/error_exception.py
akoyaapisv240/exceptions/o_auth_provider_exception.py
akoyaapisv240/http/__init__.py
akoyaapisv240/http/http_call_back.py
akoyaapisv240/http/http_method_enum.py
akoyaapisv240/http/http_request.py
akoyaapisv240/http/http_response.py
akoyaapisv240/http/auth/__init__.py
akoyaapisv240/http/auth/o_auth_2.py
akoyaapisv240/models/__init__.py
akoyaapisv240/models/accept_enum.py
akoyaapisv240/models/account.py
akoyaapisv240/models/account_1.py
akoyaapisv240/models/account_2.py
akoyaapisv240/models/account_3.py
akoyaapisv240/models/account_4.py
akoyaapisv240/models/account_5.py
akoyaapisv240/models/account_6.py
akoyaapisv240/models/account_7.py
akoyaapisv240/models/account_71.py
akoyaapisv240/models/account_72.py
akoyaapisv240/models/account_73.py
akoyaapisv240/models/account_74.py
akoyaapisv240/models/account_75.py
akoyaapisv240/models/account_76.py
akoyaapisv240/models/account_8.py
akoyaapisv240/models/account_9.py
akoyaapisv240/models/account_96.py
akoyaapisv240/models/account_category_enum.py
akoyaapisv240/models/account_contact_entity.py
akoyaapisv240/models/account_holder_entity.py
akoyaapisv240/models/account_holder_relationship_2_enum.py
akoya_sdk_sdk-1.1.2.dist-info/METADATA
akoya_sdk_sdk-1.1.2.dist-info/WHEEL
akoya_sdk_sdk-1.1.2.dist-info/top_level.txt
akoya_sdk_sdk-1.1.2.dist-info/RECORD
