Metadata-Version: 2.4
Name: akoya-sdk-sdk
Version: 1.1.2
Summary: Testing
Author-email: QA <taha.ali@apimatic.io>
Project-URL: Documentation, https://app.dev.apimatic.io/api-docs-preview/dashboard/68259b1d875bd97b51255af7/v/1_0_0#/http/step-by-step-tutorial
Requires-Python: >=3.7
License-File: LICENSE
Requires-Dist: apimatic-core>=0.2.17,~=0.2.0
Requires-Dist: apimatic-core-interfaces>=0.1.5,~=0.1.0
Requires-Dist: apimatic-requests-client-adapter>=0.1.6,~=0.1.0
Provides-Extra: testutils
Requires-Dist: pytest>=7.2.2; extra == "testutils"
Dynamic: license-file
